{
    "data": [],
    "directed": false,
    "multigraph": false,
    "elements": {
        "nodes": [
            {
                "data": {
                    "id": "0",
                    "value": 0,
                    "name": "0",
                    "X": 1117,
                    "Y": 2833,
                    "RAM": 8000,
                    "CPU": 8,
                    "IPS": 10000
                }
            },
            {
                "data": {
                    "id": "1",
                    "value": 1,
                    "name": "1",
                    "X": -554,
                    "Y": 1012,
                    "RAM": 8000,
                    "CPU": 8,
                    "IPS": 10000
                }
            },
            {
                "data": {
                    "id": "2",
                    "value": 2,
                    "name": "2",
                    "X": 3246,
                    "Y": 3706,
                    "RAM": 8000,
                    "CPU": 8,
                    "IPS": 10000
                }
            },
            {
                "data": {
                    "id": "3",
                    "value": 3,
                    "name": "3",
                    "X": 1014,
                    "Y": 450,
                    "RAM": 8000,
                    "CPU": 8,
                    "IPS": 10000
                }
            },
            {
                "data": {
                    "id": "4",
                    "value": 4,
                    "name": "4",
                    "X": 1442,
                    "Y": 2108,
                    "RAM": 8000,
                    "CPU": 8,
                    "IPS": 10000
                }
            },
            {
                "data": {
                    "id": "5",
                    "value": 5,
                    "name": "5",
                    "X": -1269,
                    "Y": 1064,
                    "RAM": 8000,
                    "CPU": 8,
                    "IPS": 10000
                }
            },
            {
                "data": {
                    "id": "6",
                    "value": 6,
                    "name": "6",
                    "X": 3452,
                    "Y": 2766,
                    "RAM": 8000,
                    "CPU": 8,
                    "IPS": 10000
                }
            },
            {
                "data": {
                    "id": "7",
                    "value": 7,
                    "name": "7",
                    "X": 4780,
                    "Y": 3079,
                    "RAM": 8000,
                    "CPU": 8,
                    "IPS": 10000
                }
            },
            {
                "data": {
                    "id": "8",
                    "value": 8,
                    "name": "8",
                    "X": 4809,
                    "Y": 2539,
                    "RAM": 8000,
                    "CPU": 8,
                    "IPS": 10000
                }
            },
            {
                "data": {
                    "id": "9",
                    "value": 9,
                    "name": "9",
                    "X": -3432,
                    "Y": 1560,
                    "RAM": 8000,
                    "CPU": 8,
                    "IPS": 10000
                }
            },
            {
                "data": {
                    "id": "10",
                    "value": 10,
                    "name": "10",
                    "X": 776,
                    "Y": -3367,
                    "RAM": 8000,
                    "CPU": 8,
                    "IPS": 10000
                }
            },
            {
                "data": {
                    "id": "11",
                    "value": 11,
                    "name": "11",
                    "X": -507,
                    "Y": -6264,
                    "RAM": 8000,
                    "CPU": 8,
                    "IPS": 10000
                }
            },
            {
                "data": {
                    "id": "12",
                    "value": 12,
                    "name": "12",
                    "X": -708,
                    "Y": 376,
                    "RAM": 8000,
                    "CPU": 8,
                    "IPS": 10000
                }
            },
            {
                "data": {
                    "id": "13",
                    "value": 13,
                    "name": "13",
                    "X": -472,
                    "Y": -3545,
                    "RAM": 8000,
                    "CPU": 8,
                    "IPS": 10000
                }
            },
            {
                "data": {
                    "id": "14",
                    "value": 14,
                    "name": "14",
                    "X": -81,
                    "Y": -634,
                    "RAM": 8000,
                    "CPU": 8,
                    "IPS": 10000
                }
            },
            {
                "data": {
                    "id": "15",
                    "value": 15,
                    "name": "15",
                    "X": 1762,
                    "Y": 3262,
                    "RAM": 8000,
                    "CPU": 8,
                    "IPS": 10000
                }
            },
            {
                "data": {
                    "id": "16",
                    "value": 16,
                    "name": "16",
                    "X": -237,
                    "Y": -7364,
                    "RAM": 8000,
                    "CPU": 8,
                    "IPS": 10000
                }
            },
            {
                "data": {
                    "id": "17",
                    "value": 17,
                    "name": "17",
                    "X": 971,
                    "Y": 4166,
                    "RAM": 8000,
                    "CPU": 8,
                    "IPS": 10000
                }
            },
            {
                "data": {
                    "id": "18",
                    "value": 18,
                    "name": "18",
                    "X": 599,
                    "Y": -1570,
                    "RAM": 8000,
                    "CPU": 8,
                    "IPS": 10000
                }
            },
            {
                "data": {
                    "id": "19",
                    "value": 19,
                    "name": "19",
                    "X": -1569,
                    "Y": -3289,
                    "RAM": 8000,
                    "CPU": 8,
                    "IPS": 10000
                }
            },
            {
                "data": {
                    "id": "20",
                    "value": 20,
                    "name": "20",
                    "X": 167,
                    "Y": 2983,
                    "RAM": 8000,
                    "CPU": 8,
                    "IPS": 10000
                }
            },
            {
                "data": {
                    "id": "21",
                    "value": 21,
                    "name": "21",
                    "X": 770,
                    "Y": -397,
                    "RAM": 8000,
                    "CPU": 8,
                    "IPS": 10000
                }
            },
            {
                "data": {
                    "id": "22",
                    "value": 22,
                    "name": "22",
                    "X": -16,
                    "Y": -1660,
                    "RAM": 8000,
                    "CPU": 8,
                    "IPS": 10000
                }
            },
            {
                "data": {
                    "id": "23",
                    "value": 23,
                    "name": "23",
                    "X": 2749,
                    "Y": 5,
                    "RAM": 8000,
                    "CPU": 8,
                    "IPS": 10000
                }
            },
            {
                "data": {
                    "id": "24",
                    "value": 24,
                    "name": "24",
                    "X": 1913,
                    "Y": 2751,
                    "RAM": 8000,
                    "CPU": 8,
                    "IPS": 10000
                }
            },
            {
                "data": {
                    "id": "25",
                    "value": 25,
                    "name": "25",
                    "X": -4627,
                    "Y": 2131,
                    "RAM": 8000,
                    "CPU": 8,
                    "IPS": 10000
                }
            },
            {
                "data": {
                    "id": "26",
                    "value": 26,
                    "name": "26",
                    "X": 88,
                    "Y": 3553,
                    "RAM": 8000,
                    "CPU": 8,
                    "IPS": 10000
                }
            },
            {
                "data": {
                    "id": "27",
                    "value": 27,
                    "name": "27",
                    "X": -2669,
                    "Y": 182,
                    "RAM": 8000,
                    "CPU": 8,
                    "IPS": 10000
                }
            },
            {
                "data": {
                    "id": "28",
                    "value": 28,
                    "name": "28",
                    "X": -271,
                    "Y": -68,
                    "RAM": 8000,
                    "CPU": 8,
                    "IPS": 10000
                }
            },
            {
                "data": {
                    "id": "29",
                    "value": 29,
                    "name": "29",
                    "X": 2286,
                    "Y": 5600,
                    "RAM": 8000,
                    "CPU": 8,
                    "IPS": 10000
                }
            },
            {
                "data": {
                    "id": "30",
                    "value": 30,
                    "name": "30",
                    "X": 1494,
                    "Y": -4503,
                    "RAM": 8000,
                    "CPU": 8,
                    "IPS": 10000
                }
            },
            {
                "data": {
                    "id": "31",
                    "value": 31,
                    "name": "31",
                    "X": 979,
                    "Y": -4571,
                    "RAM": 8000,
                    "CPU": 8,
                    "IPS": 10000
                }
            },
            {
                "data": {
                    "id": "32",
                    "value": 32,
                    "name": "32",
                    "X": 2415,
                    "Y": -4013,
                    "RAM": 8000,
                    "CPU": 8,
                    "IPS": 10000
                }
            },
            {
                "data": {
                    "id": "33",
                    "value": 33,
                    "name": "33",
                    "X": -2159,
                    "Y": -2186,
                    "RAM": 8000,
                    "CPU": 8,
                    "IPS": 10000
                }
            },
            {
                "data": {
                    "id": "34",
                    "value": 34,
                    "name": "34",
                    "X": -1951,
                    "Y": -6892,
                    "RAM": 8000,
                    "CPU": 8,
                    "IPS": 10000
                }
            },
            {
                "data": {
                    "id": "35",
                    "value": 35,
                    "name": "35",
                    "X": 1439,
                    "Y": 4011,
                    "RAM": 8000,
                    "CPU": 8,
                    "IPS": 10000
                }
            },
            {
                "data": {
                    "id": "36",
                    "value": 36,
                    "name": "36",
                    "X": -1267,
                    "Y": -8717,
                    "RAM": 8000,
                    "CPU": 8,
                    "IPS": 10000
                }
            },
            {
                "data": {
                    "id": "37",
                    "value": 37,
                    "name": "37",
                    "X": 2247,
                    "Y": 4618,
                    "RAM": 8000,
                    "CPU": 8,
                    "IPS": 10000
                }
            },
            {
                "data": {
                    "id": "38",
                    "value": 38,
                    "name": "38",
                    "X": 4955,
                    "Y": 4437,
                    "RAM": 8000,
                    "CPU": 8,
                    "IPS": 10000
                }
            },
            {
                "data": {
                    "id": "39",
                    "value": 39,
                    "name": "39",
                    "X": 438,
                    "Y": 4033,
                    "RAM": 8000,
                    "CPU": 8,
                    "IPS": 10000
                }
            },
            {
                "data": {
                    "id": "40",
                    "value": 40,
                    "name": "40",
                    "X": 1922,
                    "Y": -992,
                    "RAM": 8000,
                    "CPU": 8,
                    "IPS": 10000
                }
            },
            {
                "data": {
                    "id": "41",
                    "value": 41,
                    "name": "41",
                    "X": 2113,
                    "Y": 3569,
                    "RAM": 8000,
                    "CPU": 8,
                    "IPS": 10000
                }
            },
            {
                "data": {
                    "id": "42",
                    "value": 42,
                    "name": "42",
                    "X": -4758,
                    "Y": 1565,
                    "RAM": 8000,
                    "CPU": 8,
                    "IPS": 10000
                }
            },
            {
                "data": {
                    "id": "43",
                    "value": 43,
                    "name": "43",
                    "X": -2629,
                    "Y": -3334,
                    "RAM": 8000,
                    "CPU": 8,
                    "IPS": 10000
                }
            },
            {
                "data": {
                    "id": "44",
                    "value": 44,
                    "name": "44",
                    "X": -3096,
                    "Y": -3167,
                    "RAM": 8000,
                    "CPU": 8,
                    "IPS": 10000
                }
            },
            {
                "data": {
                    "id": "45",
                    "value": 45,
                    "name": "45",
                    "X": 2466,
                    "Y": 4209,
                    "RAM": 8000,
                    "CPU": 8,
                    "IPS": 10000
                }
            },
            {
                "data": {
                    "id": "46",
                    "value": 46,
                    "name": "46",
                    "X": -3307,
                    "Y": -2763,
                    "RAM": 8000,
                    "CPU": 8,
                    "IPS": 10000
                }
            },
            {
                "data": {
                    "id": "47",
                    "value": 47,
                    "name": "47",
                    "X": -3402,
                    "Y": -2278,
                    "RAM": 8000,
                    "CPU": 8,
                    "IPS": 10000
                }
            },
            {
                "data": {
                    "id": "48",
                    "value": 48,
                    "name": "48",
                    "X": -672,
                    "Y": -9728,
                    "RAM": 8000,
                    "CPU": 8,
                    "IPS": 10000
                }
            },
            {
                "data": {
                    "id": "49",
                    "value": 49,
                    "name": "49",
                    "X": -1903,
                    "Y": 1456,
                    "RAM": 8000,
                    "CPU": 8,
                    "IPS": 10000
                }
            },
            {
                "data": {
                    "id": "50",
                    "value": 50,
                    "name": "50",
                    "X": 2356,
                    "Y": 6986,
                    "RAM": 8000,
                    "CPU": 8,
                    "IPS": 10000
                }
            },
            {
                "data": {
                    "id": "51",
                    "value": 51,
                    "name": "51",
                    "X": -4468,
                    "Y": -449,
                    "RAM": 8000,
                    "CPU": 8,
                    "IPS": 10000
                }
            },
            {
                "data": {
                    "id": "52",
                    "value": 52,
                    "name": "52",
                    "X": -2203,
                    "Y": -9347,
                    "RAM": 8000,
                    "CPU": 8,
                    "IPS": 10000
                }
            },
            {
                "data": {
                    "id": "53",
                    "value": 53,
                    "name": "53",
                    "X": -3079,
                    "Y": -7319,
                    "RAM": 8000,
                    "CPU": 8,
                    "IPS": 10000
                }
            },
            {
                "data": {
                    "id": "54",
                    "value": 54,
                    "name": "54",
                    "X": -2787,
                    "Y": 2303,
                    "RAM": 8000,
                    "CPU": 8,
                    "IPS": 10000
                }
            },
            {
                "data": {
                    "id": "55",
                    "value": 55,
                    "name": "55",
                    "X": -334,
                    "Y": 5393,
                    "RAM": 8000,
                    "CPU": 8,
                    "IPS": 10000
                }
            },
            {
                "data": {
                    "id": "56",
                    "value": 56,
                    "name": "56",
                    "X": -5768,
                    "Y": -847,
                    "RAM": 8000,
                    "CPU": 8,
                    "IPS": 10000
                }
            },
            {
                "data": {
                    "id": "57",
                    "value": 57,
                    "name": "57",
                    "X": 6164,
                    "Y": 4973,
                    "RAM": 8000,
                    "CPU": 8,
                    "IPS": 10000
                }
            },
            {
                "data": {
                    "id": "58",
                    "value": 58,
                    "name": "58",
                    "X": 4038,
                    "Y": -329,
                    "RAM": 8000,
                    "CPU": 8,
                    "IPS": 10000
                }
            },
            {
                "data": {
                    "id": "59",
                    "value": 59,
                    "name": "59",
                    "X": 709,
                    "Y": 3590,
                    "RAM": 8000,
                    "CPU": 8,
                    "IPS": 10000
                }
            },
            {
                "data": {
                    "id": "60",
                    "value": 60,
                    "name": "60",
                    "X": -1041,
                    "Y": 6357,
                    "RAM": 8000,
                    "CPU": 8,
                    "IPS": 10000
                }
            },
            {
                "data": {
                    "id": "61",
                    "value": 61,
                    "name": "61",
                    "X": 2920,
                    "Y": 6846,
                    "RAM": 8000,
                    "CPU": 8,
                    "IPS": 10000
                }
            },
            {
                "data": {
                    "id": "62",
                    "value": 62,
                    "name": "62",
                    "X": 1705,
                    "Y": -4020,
                    "RAM": 8000,
                    "CPU": 8,
                    "IPS": 10000
                }
            },
            {
                "data": {
                    "id": "63",
                    "value": 63,
                    "name": "63",
                    "X": -119,
                    "Y": -2966,
                    "RAM": 8000,
                    "CPU": 8,
                    "IPS": 10000
                }
            },
            {
                "data": {
                    "id": "64",
                    "value": 64,
                    "name": "64",
                    "X": -2112,
                    "Y": 567,
                    "RAM": 8000,
                    "CPU": 8,
                    "IPS": 10000
                }
            },
            {
                "data": {
                    "id": "65",
                    "value": 65,
                    "name": "65",
                    "X": -1099,
                    "Y": -10000,
                    "RAM": 8000,
                    "CPU": 8,
                    "IPS": 10000
                }
            },
            {
                "data": {
                    "id": "66",
                    "value": 66,
                    "name": "66",
                    "X": -1560,
                    "Y": 7117,
                    "RAM": 8000,
                    "CPU": 8,
                    "IPS": 10000
                }
            },
            {
                "data": {
                    "id": "67",
                    "value": 67,
                    "name": "67",
                    "X": 3565,
                    "Y": -4489,
                    "RAM": 8000,
                    "CPU": 8,
                    "IPS": 10000
                }
            },
            {
                "data": {
                    "id": "68",
                    "value": 68,
                    "name": "68",
                    "X": -962,
                    "Y": -2522,
                    "RAM": 8000,
                    "CPU": 8,
                    "IPS": 10000
                }
            },
            {
                "data": {
                    "id": "69",
                    "value": 69,
                    "name": "69",
                    "X": -1550,
                    "Y": -9911,
                    "RAM": 8000,
                    "CPU": 8,
                    "IPS": 10000
                }
            },
            {
                "data": {
                    "id": "70",
                    "value": 70,
                    "name": "70",
                    "X": -3135,
                    "Y": 845,
                    "RAM": 8000,
                    "CPU": 8,
                    "IPS": 10000
                }
            },
            {
                "data": {
                    "id": "71",
                    "value": 71,
                    "name": "71",
                    "X": -1996,
                    "Y": -9772,
                    "RAM": 8000,
                    "CPU": 8,
                    "IPS": 10000
                }
            },
            {
                "data": {
                    "id": "72",
                    "value": 72,
                    "name": "72",
                    "X": -1956,
                    "Y": 8331,
                    "RAM": 8000,
                    "CPU": 8,
                    "IPS": 10000
                }
            },
            {
                "data": {
                    "id": "73",
                    "value": 73,
                    "name": "73",
                    "X": -1832,
                    "Y": -3932,
                    "RAM": 8000,
                    "CPU": 8,
                    "IPS": 10000
                }
            },
            {
                "data": {
                    "id": "74",
                    "value": 74,
                    "name": "74",
                    "X": 2160,
                    "Y": 2219,
                    "RAM": 8000,
                    "CPU": 8,
                    "IPS": 10000
                }
            },
            {
                "data": {
                    "id": "75",
                    "value": 75,
                    "name": "75",
                    "X": -443,
                    "Y": 6676,
                    "RAM": 8000,
                    "CPU": 8,
                    "IPS": 10000
                }
            },
            {
                "data": {
                    "id": "76",
                    "value": 76,
                    "name": "76",
                    "X": 3426,
                    "Y": 5246,
                    "RAM": 8000,
                    "CPU": 8,
                    "IPS": 10000
                }
            },
            {
                "data": {
                    "id": "77",
                    "value": 77,
                    "name": "77",
                    "X": -1382,
                    "Y": -5095,
                    "RAM": 8000,
                    "CPU": 8,
                    "IPS": 10000
                }
            },
            {
                "data": {
                    "id": "78",
                    "value": 78,
                    "name": "78",
                    "X": -2474,
                    "Y": 7975,
                    "RAM": 8000,
                    "CPU": 8,
                    "IPS": 10000
                }
            },
            {
                "data": {
                    "id": "79",
                    "value": 79,
                    "name": "79",
                    "X": 2405,
                    "Y": 2849,
                    "RAM": 8000,
                    "CPU": 8,
                    "IPS": 10000
                }
            }
        ],
        "edges": [
            {
                "data": {
                    "source": 0,
                    "target": 1,
                    "PS": 300000000,
                    "COST": 1,
                    "SNR": 30,
                    "bandwidth": 25000
                }
            },
            {
                "data": {
                    "source": 0,
                    "target": 2,
                    "PS": 300000000,
                    "COST": 1,
                    "SNR": 30,
                    "bandwidth": 25000
                }
            },
            {
                "data": {
                    "source": 0,
                    "target": 3,
                    "PS": 300000000,
                    "COST": 1,
                    "SNR": 30,
                    "bandwidth": 25000
                }
            },
            {
                "data": {
                    "source": 0,
                    "target": 4,
                    "PS": 300000000,
                    "COST": 1,
                    "SNR": 30,
                    "bandwidth": 25000
                }
            },
            {
                "data": {
                    "source": 0,
                    "target": 6,
                    "PS": 300000000,
                    "COST": 1,
                    "SNR": 30,
                    "bandwidth": 25000
                }
            },
            {
                "data": {
                    "source": 0,
                    "target": 12,
                    "PS": 300000000,
                    "COST": 1,
                    "SNR": 30,
                    "bandwidth": 25000
                }
            },
            {
                "data": {
                    "source": 0,
                    "target": 17,
                    "PS": 300000000,
                    "COST": 1,
                    "SNR": 30,
                    "bandwidth": 25000
                }
            },
            {
                "data": {
                    "source": 0,
                    "target": 20,
                    "PS": 300000000,
                    "COST": 1,
                    "SNR": 30,
                    "bandwidth": 25000
                }
            },
            {
                "data": {
                    "source": 0,
                    "target": 24,
                    "PS": 300000000,
                    "COST": 1,
                    "SNR": 30,
                    "bandwidth": 25000
                }
            },
            {
                "data": {
                    "source": 0,
                    "target": 26,
                    "PS": 300000000,
                    "COST": 1,
                    "SNR": 30,
                    "bandwidth": 25000
                }
            },
            {
                "data": {
                    "source": 0,
                    "target": 35,
                    "PS": 300000000,
                    "COST": 1,
                    "SNR": 30,
                    "bandwidth": 25000
                }
            },
            {
                "data": {
                    "source": 0,
                    "target": 39,
                    "PS": 300000000,
                    "COST": 1,
                    "SNR": 30,
                    "bandwidth": 25000
                }
            },
            {
                "data": {
                    "source": 0,
                    "target": 41,
                    "PS": 300000000,
                    "COST": 1,
                    "SNR": 30,
                    "bandwidth": 25000
                }
            },
            {
                "data": {
                    "source": 0,
                    "target": 45,
                    "PS": 300000000,
                    "COST": 1,
                    "SNR": 30,
                    "bandwidth": 25000
                }
            },
            {
                "data": {
                    "source": 0,
                    "target": 55,
                    "PS": 300000000,
                    "COST": 1,
                    "SNR": 30,
                    "bandwidth": 25000
                }
            },
            {
                "data": {
                    "source": 0,
                    "target": 59,
                    "PS": 300000000,
                    "COST": 1,
                    "SNR": 30,
                    "bandwidth": 25000
                }
            },
            {
                "data": {
                    "source": 0,
                    "target": 74,
                    "PS": 300000000,
                    "COST": 1,
                    "SNR": 30,
                    "bandwidth": 25000
                }
            },
            {
                "data": {
                    "source": 0,
                    "target": 79,
                    "PS": 300000000,
                    "COST": 1,
                    "SNR": 30,
                    "bandwidth": 25000
                }
            },
            {
                "data": {
                    "source": 1,
                    "target": 14,
                    "PS": 300000000,
                    "COST": 1,
                    "SNR": 30,
                    "bandwidth": 25000
                }
            },
            {
                "data": {
                    "source": 1,
                    "target": 27,
                    "PS": 300000000,
                    "COST": 1,
                    "SNR": 30,
                    "bandwidth": 25000
                }
            },
            {
                "data": {
                    "source": 2,
                    "target": 38,
                    "PS": 300000000,
                    "COST": 1,
                    "SNR": 30,
                    "bandwidth": 25000
                }
            },
            {
                "data": {
                    "source": 3,
                    "target": 5,
                    "PS": 300000000,
                    "COST": 1,
                    "SNR": 30,
                    "bandwidth": 25000
                }
            },
            {
                "data": {
                    "source": 3,
                    "target": 10,
                    "PS": 300000000,
                    "COST": 1,
                    "SNR": 30,
                    "bandwidth": 25000
                }
            },
            {
                "data": {
                    "source": 3,
                    "target": 15,
                    "PS": 300000000,
                    "COST": 1,
                    "SNR": 30,
                    "bandwidth": 25000
                }
            },
            {
                "data": {
                    "source": 3,
                    "target": 23,
                    "PS": 300000000,
                    "COST": 1,
                    "SNR": 30,
                    "bandwidth": 25000
                }
            },
            {
                "data": {
                    "source": 5,
                    "target": 9,
                    "PS": 300000000,
                    "COST": 1,
                    "SNR": 30,
                    "bandwidth": 25000
                }
            },
            {
                "data": {
                    "source": 6,
                    "target": 7,
                    "PS": 300000000,
                    "COST": 1,
                    "SNR": 30,
                    "bandwidth": 25000
                }
            },
            {
                "data": {
                    "source": 6,
                    "target": 8,
                    "PS": 300000000,
                    "COST": 1,
                    "SNR": 30,
                    "bandwidth": 25000
                }
            },
            {
                "data": {
                    "source": 9,
                    "target": 25,
                    "PS": 300000000,
                    "COST": 1,
                    "SNR": 30,
                    "bandwidth": 25000
                }
            },
            {
                "data": {
                    "source": 9,
                    "target": 42,
                    "PS": 300000000,
                    "COST": 1,
                    "SNR": 30,
                    "bandwidth": 25000
                }
            },
            {
                "data": {
                    "source": 10,
                    "target": 11,
                    "PS": 300000000,
                    "COST": 1,
                    "SNR": 30,
                    "bandwidth": 25000
                }
            },
            {
                "data": {
                    "source": 10,
                    "target": 13,
                    "PS": 300000000,
                    "COST": 1,
                    "SNR": 30,
                    "bandwidth": 25000
                }
            },
            {
                "data": {
                    "source": 10,
                    "target": 30,
                    "PS": 300000000,
                    "COST": 1,
                    "SNR": 30,
                    "bandwidth": 25000
                }
            },
            {
                "data": {
                    "source": 10,
                    "target": 31,
                    "PS": 300000000,
                    "COST": 1,
                    "SNR": 30,
                    "bandwidth": 25000
                }
            },
            {
                "data": {
                    "source": 10,
                    "target": 32,
                    "PS": 300000000,
                    "COST": 1,
                    "SNR": 30,
                    "bandwidth": 25000
                }
            },
            {
                "data": {
                    "source": 10,
                    "target": 62,
                    "PS": 300000000,
                    "COST": 1,
                    "SNR": 30,
                    "bandwidth": 25000
                }
            },
            {
                "data": {
                    "source": 10,
                    "target": 63,
                    "PS": 300000000,
                    "COST": 1,
                    "SNR": 30,
                    "bandwidth": 25000
                }
            },
            {
                "data": {
                    "source": 11,
                    "target": 16,
                    "PS": 300000000,
                    "COST": 1,
                    "SNR": 30,
                    "bandwidth": 25000
                }
            },
            {
                "data": {
                    "source": 11,
                    "target": 34,
                    "PS": 300000000,
                    "COST": 1,
                    "SNR": 30,
                    "bandwidth": 25000
                }
            },
            {
                "data": {
                    "source": 11,
                    "target": 36,
                    "PS": 300000000,
                    "COST": 1,
                    "SNR": 30,
                    "bandwidth": 25000
                }
            },
            {
                "data": {
                    "source": 12,
                    "target": 21,
                    "PS": 300000000,
                    "COST": 1,
                    "SNR": 30,
                    "bandwidth": 25000
                }
            },
            {
                "data": {
                    "source": 12,
                    "target": 28,
                    "PS": 300000000,
                    "COST": 1,
                    "SNR": 30,
                    "bandwidth": 25000
                }
            },
            {
                "data": {
                    "source": 12,
                    "target": 33,
                    "PS": 300000000,
                    "COST": 1,
                    "SNR": 30,
                    "bandwidth": 25000
                }
            },
            {
                "data": {
                    "source": 12,
                    "target": 49,
                    "PS": 300000000,
                    "COST": 1,
                    "SNR": 30,
                    "bandwidth": 25000
                }
            },
            {
                "data": {
                    "source": 12,
                    "target": 64,
                    "PS": 300000000,
                    "COST": 1,
                    "SNR": 30,
                    "bandwidth": 25000
                }
            },
            {
                "data": {
                    "source": 13,
                    "target": 19,
                    "PS": 300000000,
                    "COST": 1,
                    "SNR": 30,
                    "bandwidth": 25000
                }
            },
            {
                "data": {
                    "source": 14,
                    "target": 18,
                    "PS": 300000000,
                    "COST": 1,
                    "SNR": 30,
                    "bandwidth": 25000
                }
            },
            {
                "data": {
                    "source": 14,
                    "target": 22,
                    "PS": 300000000,
                    "COST": 1,
                    "SNR": 30,
                    "bandwidth": 25000
                }
            },
            {
                "data": {
                    "source": 15,
                    "target": 29,
                    "PS": 300000000,
                    "COST": 1,
                    "SNR": 30,
                    "bandwidth": 25000
                }
            },
            {
                "data": {
                    "source": 15,
                    "target": 37,
                    "PS": 300000000,
                    "COST": 1,
                    "SNR": 30,
                    "bandwidth": 25000
                }
            },
            {
                "data": {
                    "source": 21,
                    "target": 40,
                    "PS": 300000000,
                    "COST": 1,
                    "SNR": 30,
                    "bandwidth": 25000
                }
            },
            {
                "data": {
                    "source": 23,
                    "target": 58,
                    "PS": 300000000,
                    "COST": 1,
                    "SNR": 30,
                    "bandwidth": 25000
                }
            },
            {
                "data": {
                    "source": 27,
                    "target": 51,
                    "PS": 300000000,
                    "COST": 1,
                    "SNR": 30,
                    "bandwidth": 25000
                }
            },
            {
                "data": {
                    "source": 29,
                    "target": 50,
                    "PS": 300000000,
                    "COST": 1,
                    "SNR": 30,
                    "bandwidth": 25000
                }
            },
            {
                "data": {
                    "source": 29,
                    "target": 61,
                    "PS": 300000000,
                    "COST": 1,
                    "SNR": 30,
                    "bandwidth": 25000
                }
            },
            {
                "data": {
                    "source": 32,
                    "target": 67,
                    "PS": 300000000,
                    "COST": 1,
                    "SNR": 30,
                    "bandwidth": 25000
                }
            },
            {
                "data": {
                    "source": 33,
                    "target": 43,
                    "PS": 300000000,
                    "COST": 1,
                    "SNR": 30,
                    "bandwidth": 25000
                }
            },
            {
                "data": {
                    "source": 33,
                    "target": 44,
                    "PS": 300000000,
                    "COST": 1,
                    "SNR": 30,
                    "bandwidth": 25000
                }
            },
            {
                "data": {
                    "source": 33,
                    "target": 46,
                    "PS": 300000000,
                    "COST": 1,
                    "SNR": 30,
                    "bandwidth": 25000
                }
            },
            {
                "data": {
                    "source": 33,
                    "target": 47,
                    "PS": 300000000,
                    "COST": 1,
                    "SNR": 30,
                    "bandwidth": 25000
                }
            },
            {
                "data": {
                    "source": 33,
                    "target": 73,
                    "PS": 300000000,
                    "COST": 1,
                    "SNR": 30,
                    "bandwidth": 25000
                }
            },
            {
                "data": {
                    "source": 34,
                    "target": 53,
                    "PS": 300000000,
                    "COST": 1,
                    "SNR": 30,
                    "bandwidth": 25000
                }
            },
            {
                "data": {
                    "source": 36,
                    "target": 48,
                    "PS": 300000000,
                    "COST": 1,
                    "SNR": 30,
                    "bandwidth": 25000
                }
            },
            {
                "data": {
                    "source": 36,
                    "target": 52,
                    "PS": 300000000,
                    "COST": 1,
                    "SNR": 30,
                    "bandwidth": 25000
                }
            },
            {
                "data": {
                    "source": 36,
                    "target": 65,
                    "PS": 300000000,
                    "COST": 1,
                    "SNR": 30,
                    "bandwidth": 25000
                }
            },
            {
                "data": {
                    "source": 36,
                    "target": 69,
                    "PS": 300000000,
                    "COST": 1,
                    "SNR": 30,
                    "bandwidth": 25000
                }
            },
            {
                "data": {
                    "source": 36,
                    "target": 71,
                    "PS": 300000000,
                    "COST": 1,
                    "SNR": 30,
                    "bandwidth": 25000
                }
            },
            {
                "data": {
                    "source": 38,
                    "target": 57,
                    "PS": 300000000,
                    "COST": 1,
                    "SNR": 30,
                    "bandwidth": 25000
                }
            },
            {
                "data": {
                    "source": 45,
                    "target": 76,
                    "PS": 300000000,
                    "COST": 1,
                    "SNR": 30,
                    "bandwidth": 25000
                }
            },
            {
                "data": {
                    "source": 49,
                    "target": 54,
                    "PS": 300000000,
                    "COST": 1,
                    "SNR": 30,
                    "bandwidth": 25000
                }
            },
            {
                "data": {
                    "source": 51,
                    "target": 56,
                    "PS": 300000000,
                    "COST": 1,
                    "SNR": 30,
                    "bandwidth": 25000
                }
            },
            {
                "data": {
                    "source": 55,
                    "target": 60,
                    "PS": 300000000,
                    "COST": 1,
                    "SNR": 30,
                    "bandwidth": 25000
                }
            },
            {
                "data": {
                    "source": 55,
                    "target": 66,
                    "PS": 300000000,
                    "COST": 1,
                    "SNR": 30,
                    "bandwidth": 25000
                }
            },
            {
                "data": {
                    "source": 55,
                    "target": 75,
                    "PS": 300000000,
                    "COST": 1,
                    "SNR": 30,
                    "bandwidth": 25000
                }
            },
            {
                "data": {
                    "source": 63,
                    "target": 68,
                    "PS": 300000000,
                    "COST": 1,
                    "SNR": 30,
                    "bandwidth": 25000
                }
            },
            {
                "data": {
                    "source": 64,
                    "target": 70,
                    "PS": 300000000,
                    "COST": 1,
                    "SNR": 30,
                    "bandwidth": 25000
                }
            },
            {
                "data": {
                    "source": 66,
                    "target": 72,
                    "PS": 300000000,
                    "COST": 1,
                    "SNR": 30,
                    "bandwidth": 25000
                }
            },
            {
                "data": {
                    "source": 66,
                    "target": 78,
                    "PS": 300000000,
                    "COST": 1,
                    "SNR": 30,
                    "bandwidth": 25000
                }
            },
            {
                "data": {
                    "source": 73,
                    "target": 77,
                    "PS": 300000000,
                    "COST": 1,
                    "SNR": 30,
                    "bandwidth": 25000
                }
            }
        ]
    }
}